.gitignore
MANIFEST.in
README
setup.py
charon/__init__.py
charon/api.py
charon/global.example
charon/loader.py
charon/server.py
charon.egg-info/PKG-INFO
charon.egg-info/SOURCES.txt
charon.egg-info/dependency_links.txt
charon.egg-info/entry_points.txt
charon.egg-info/not-zip-safe
charon.egg-info/requires.txt
charon.egg-info/top_level.txt