Metadata-Version: 1.0
Name: charon
Version: 0.1.2
Summary: A set of tools to manage the load balancer HAProxy
Home-page: http://pypi.python.org/pypi/charon/
Author: Matt Long
Author-email: matt@mattlong.org
License: MIT
Platform: UNKNOWN
Classifier: Programming Language :: Python
Classifier: Programming Language :: Python :: 2
Classifier: License :: OSI Approved :: MIT License
Classifier: Operating System :: Unix
Classifier: Development Status :: 3 - Alpha
Classifier: Intended Audience :: Developers
Classifier: Intended Audience :: System Administrators
Classifier: Topic :: Internet :: WWW/HTTP
Classifier: Topic :: Software Development :: Libraries :: Python Modules
